LICENSE
apminsight/__init__.py
apminsight/agent.py
apminsight/agentfactory.py
apminsight/collector/__init__.py
apminsight/collector/connhandler.py
apminsight/collector/datahandler.py
apminsight/collector/insinfo.py
apminsight/collector/reqhandler.py
apminsight/collector/rescodes.py
apminsight/collector/reshandler.py
apminsight/config/__init__.py
apminsight/config/configuration.py
apminsight/config/threshold.py
apminsight/constants.py
apminsight/context.py
apminsight/contrib/__init__.py
apminsight/contrib/django/__init__.py
apminsight/contrib/django/apps.py
apminsight/contrib/django/wrapper.py
apminsight/instrumentation/__init__.py
apminsight/instrumentation/dbapi2.py
apminsight/instrumentation/modules.py
apminsight/instrumentation/packages/__init__.py
apminsight/instrumentation/packages/django.py
apminsight/instrumentation/packages/flask.py
apminsight/instrumentation/packages/jinja2.py
apminsight/instrumentation/packages/mysql.py
apminsight/instrumentation/packages/psycopg2.py
apminsight/instrumentation/packages/pymemcache.py
apminsight/instrumentation/packages/redis.py
apminsight/instrumentation/packages/sqlite.py
apminsight/instrumentation/psycopg2_wrapper.py
apminsight/instrumentation/util.py
apminsight/instrumentation/wrapper.py
apminsight/logger.py
apminsight/metric/__init__.py
apminsight/metric/apdexmetric.py
apminsight/metric/component.py
apminsight/metric/dbmetric.py
apminsight/metric/dbtracker.py
apminsight/metric/error.py
apminsight/metric/metricstore.py
apminsight/metric/tracker.py
apminsight/metric/txn.py
apminsight/util.py
apminsight_site24x7_py-1.0.0.dist-info/LICENSE
apminsight_site24x7_py-1.0.0.dist-info/WHEEL
apminsight_site24x7_py-1.0.0.dist-info/METADATA
apminsight_site24x7_py-1.0.0.dist-info/RECORD
