Metadata-Version: 2.1
Name: apminsight-site24x7-py
Version: 1.0.0
Summary: site24x7 monitoring package
Home-page: https://github.com/Wealize/apminsight-site24x7-py
License: MIT
Keywords: monitoring,site24x7
Author: Wealize
Author-email: ops@wealize.digital
Maintainer: Wealize
Maintainer-email: ops@wealize.digital
Requires-Python: >=3.8,<4.0
Classifier: Development Status :: 5 - Production/Stable
Classifier: Environment :: Plugins
Classifier: Framework :: Django
Classifier: Framework :: Flask
Classifier: Intended Audience :: Developers
Classifier: Intended Audience :: System Administrators
Classifier: License :: OSI Approved :: MIT License
Classifier: Natural Language :: English
Classifier: Natural Language :: Spanish
Classifier: Operating System :: OS Independent
Classifier: Programming Language :: Python
Classifier: Programming Language :: Python :: 3
Classifier: Programming Language :: Python :: 3.8
Classifier: Programming Language :: Python :: 3.9
Classifier: Topic :: Software Development
Classifier: Topic :: Software Development :: Bug Tracking
Classifier: Topic :: Software Development :: Libraries :: Python Modules
Classifier: Topic :: System :: Monitoring
Classifier: Topic :: System :: Systems Administration
Requires-Dist: requests (>=2.25.1,<3.0.0)
Project-URL: Documentation, https://github.com/Wealize/apminsight-site24x7-py
Project-URL: Repository, https://github.com/Wealize/apminsight-site24x7-py
